qmp/__init__.py
qmp/__main__.py
qmp/_version.py
qmp/version.py
qmp/algorithms/chop_imag.py
qmp/algorithms/guide.py
qmp/algorithms/haar.py
qmp/algorithms/pert.py
qmp/algorithms/pretrain.py
qmp/algorithms/vmc.py
qmp/hamiltonian/__init__.py
qmp/hamiltonian/_hamiltonian.cpp
qmp/hamiltonian/_hamiltonian_cpu.cpp
qmp/hamiltonian/_hamiltonian_cuda.cu
qmp/hamiltonian/hamiltonian.py
qmp/models/__init__.py
qmp/models/fcidump.py
qmp/models/hubbard.py
qmp/models/ising.py
qmp/models/openfermion.py
qmp/networks/__init__.py
qmp/networks/mlp.py
qmp/networks/transformers.py
qmp/utility/__init__.py
qmp/utility/bitspack.py
qmp/utility/context.py
qmp/utility/losses.py
qmp/utility/model_dict.py
qmp/utility/optimizer.py
qmp/utility/random_engine.py
qmp/utility/subcommand_dict.py
qmp_kit-0.0.56.dist-info/licenses/LICENSE.md
qmp_kit-0.0.56.dist-info/METADATA
qmp_kit-0.0.56.dist-info/WHEEL
qmp_kit-0.0.56.dist-info/entry_points.txt
qmp_kit-0.0.56.dist-info/top_level.txt
qmp_kit-0.0.56.dist-info/RECORD
