Metadata-Version: 2.4
Name: qmp-kit
Version: 0.0.56
Summary: Quantum Manybody Problem
Author-email: Hao Zhang <hzhangxyz@outlook.com>
License-Expression: GPL-3.0-or-later
Project-URL: Homepage, https://github.com/USTC-KnowledgeComputingLab/qmp-kit
Project-URL: Documentation, https://github.com/USTC-KnowledgeComputingLab/qmp-kit
Project-URL: Repository, https://github.com/USTC-KnowledgeComputingLab/qmp-kit.git
Project-URL: Issues, https://github.com/USTC-KnowledgeComputingLab/qmp-kit/issues
Keywords: quantum,manybody,quantum-chemistry,quantum-simulation,molecular-simulation,algorithms,simulation,wave-function,ground-state,ansatz,torch,pytorch
Classifier: Programming Language :: C++
Classifier: Programming Language :: Python :: 3
Classifier: Environment :: GPU :: NVIDIA CUDA
Classifier: Topic :: Scientific/Engineering :: Mathematics
Classifier: Topic :: Scientific/Engineering :: Physics
Classifier: Topic :: Scientific/Engineering :: Chemistry
Requires-Python: >=3.12
License-File: LICENSE.md
Requires-Dist: platformdirs>=4.5.1
Requires-Dist: numpy>=2.3.5
Requires-Dist: scipy>=1.16.3
Requires-Dist: torch>=2.9.1
Requires-Dist: pybind11>=3.0.1
Requires-Dist: ninja>=1.13.0
Requires-Dist: hydra-core>=1.3.2
Requires-Dist: openfermion>=1.7.1
Requires-Dist: tensorboard>=2.20.0
Requires-Dist: dacite>=1.9.2
Provides-Extra: dev
Requires-Dist: mypy>=1.19.1; extra == "dev"
Requires-Dist: ruff>=0.14.10; extra == "dev"
Requires-Dist: types-pyyaml>=6.0.12; extra == "dev"
Dynamic: license-file
